CHANGES.rst
CONTRIBUTORS.rst
README.rst
bootstrap.py
buildout.cfg
i18n.sh
setup.py
docs/LICENSE.GPL
docs/LICENSE.txt
src/wm/__init__.py
src/wm.showhidecolumns.egg-info/PKG-INFO
src/wm.showhidecolumns.egg-info/SOURCES.txt
src/wm.showhidecolumns.egg-info/dependency_links.txt
src/wm.showhidecolumns.egg-info/entry_points.txt
src/wm.showhidecolumns.egg-info/namespace_packages.txt
src/wm.showhidecolumns.egg-info/not-zip-safe
src/wm.showhidecolumns.egg-info/paster_plugins.txt
src/wm.showhidecolumns.egg-info/requires.txt
src/wm.showhidecolumns.egg-info/top_level.txt
src/wm/showhidecolumns/__init__.py
src/wm/showhidecolumns/configure.zcml
src/wm/showhidecolumns/extender.py
src/wm/showhidecolumns/interfaces.py
src/wm/showhidecolumns/testing.py
src/wm/showhidecolumns/browser/__init__.py
src/wm/showhidecolumns/browser/configure.zcml
src/wm/showhidecolumns/locales/manual.pot
src/wm/showhidecolumns/locales/wm.showhidecolumns.pot
src/wm/showhidecolumns/locales/de/LC_MESSAGES/wm.showhidecolumns.po
src/wm/showhidecolumns/profiles/default/browserlayer.xml
src/wm/showhidecolumns/profiles/default/metadata.xml
src/wm/showhidecolumns/profiles/default/viewlets.xml
src/wm/showhidecolumns/profiles/testing/metadata.xml
src/wm/showhidecolumns/tests/__init__.py
src/wm/showhidecolumns/tests/test_example.py