Metadata-Version: 1.1
Name: wm.showhidecolumns
Version: 0.1rc1
Summary: Allows to show or hide the left or right portlet column per document
Home-page: https://github.com/webmeisterei/wm.showhidecolumns
Author: Harald Friessnegger
Author-email: harald (at) webmeisterei dot com
License: gpl
Keywords: plone,collective,portlets,columns,portletcolumn
Platform: UNKNOWN
Classifier: Environment :: Web Environment
Classifier: Framework :: Plone
Classifier: Operating System :: OS Independent
Classifier: Programming Language :: Python
Classifier: Programming Language :: Python :: 2.6
Classifier: Topic :: Software Development :: Libraries :: Python Modules
